server/__init__.py
server/server.py
server/server_database.py
server/server_gui.py
server/common/__init__.py
server/common/decorators.py
server/common/descriptors.py
server/common/errors.py
server/common/metaclasses.py
server/common/utils.py
server/common/variables.py
server/logs/__init__.py
server/logs/client_log_config.py
server/logs/server_log_config.py
server/server/__init__.py
server/server/add_user.py
server/server/config_window.py
server/server/core.py
server/server/database.py
server/server/main_window.py
server/server/remove_user.py
server/server/stat_window.py
server/unit_tests/__init__.py
server/unit_tests/test_client.py
server/unit_tests/test_server.py
server/unit_tests/test_utils.py
me55enger_server-0.0.2.dist-info/METADATA
me55enger_server-0.0.2.dist-info/WHEEL
me55enger_server-0.0.2.dist-info/top_level.txt
me55enger_server-0.0.2.dist-info/RECORD
